Metadata-Version: 1.0
Name: names
Version: 0.2
Summary: Generate random names
Home-page: https://github.com/treyhunner/names
Author: Trey Hunner
Author-email: UNKNOWN
License: MIT
Platform: UNKNOWN
